affectlog_widgets/__init__.py
affectlog_widgets/__version__.py
affectlog_widgets/constants.py
affectlog_widgets/dashboard.py
affectlog_widgets/error_analysis_constants.py
affectlog_widgets/error_analysis_dashboard.py
affectlog_widgets/error_analysis_dashboard_input.py
affectlog_widgets/error_handling.py
affectlog_widgets/explanation_constants.py
affectlog_widgets/explanation_dashboard.py
affectlog_widgets/explanation_dashboard_input.py
affectlog_widgets/fairness_dashboard.py
affectlog_widgets/fairness_metric_calculation.py
affectlog_widgets/interfaces.py
affectlog_widgets/model_analysis_dashboard.py
affectlog_widgets/model_performance_dashboard.py
affectlog_widgets/trustworthyai_dashboard.py
affectlog_widgets/trustworthyai_dashboard_input.py
affectlog_widgets-0.0.6.dist-info/LICENSE
affectlog_widgets-0.0.6.dist-info/METADATA
affectlog_widgets-0.0.6.dist-info/WHEEL
affectlog_widgets-0.0.6.dist-info/top_level.txt
affectlog_widgets-0.0.6.dist-info/RECORD
